setup.cfg
setup.py
sptrans/__init__.py
sptrans/v0.py
sptrans.egg-info/PKG-INFO
sptrans.egg-info/SOURCES.txt
sptrans.egg-info/dependency_links.txt
sptrans.egg-info/entry_points.txt
sptrans.egg-info/requires.txt
sptrans.egg-info/top_level.txt
sptrans.egg-info/zip-safe