Metadata-Version: 1.1
Name: sptrans
Version: 0.1.0
Summary: Python library for the SPTrans API. Read the docs here: http://sptrans.readthedocs.org/
Home-page: http://sptrans.readthedocs.org/
Author: Diogo Baeder
Author-email: diogobaeder@yahoo.com.br
License: BSD 2-clause
Keywords: sptrans api transporte sp
Platform: UNKNOWN
Classifier: Development Status :: 3 - Alpha
Classifier: License :: OSI Approved :: BSD License
Classifier: Natural Language :: English
Classifier: Programming Language :: Python :: 2.7
Classifier: Programming Language :: Python :: 3.3
Classifier: Topic :: Internet :: WWW/HTTP
Classifier: Topic :: Scientific/Engineering :: GIS
Classifier: Topic :: Software Development :: Libraries :: Python Modules
